cxcsvtopandas/__init__.py
cxcsvtopandas/dataframeloader.py
cxcsvtopandas-0.1.4.dist-info/METADATA
cxcsvtopandas-0.1.4.dist-info/WHEEL
cxcsvtopandas-0.1.4.dist-info/top_level.txt
cxcsvtopandas-0.1.4.dist-info/RECORD
