Metadata-Version: 2.1
Name: cxcsvtopandas
Version: 0.1.4
Summary: Python package for SAI propritary report generation.
Home-page: https://github.com/amitgupta7/base-cxpandascsvloader
Author: Amit Gupta
Author-email: amit864@gmail.com
Classifier: Programming Language :: Python :: 3
Classifier: License :: OSI Approved :: MIT License
Classifier: Operating System :: OS Independent
Requires-Python: >=3.6
Requires-Dist: pandas==2.2.2
Requires-Dist: plotly==5.22.0
